oauth2_authcodeflow/__init__.py
oauth2_authcodeflow/apps.py
oauth2_authcodeflow/auth.py
oauth2_authcodeflow/conf.py
oauth2_authcodeflow/constants.py
oauth2_authcodeflow/management/__init__.py
oauth2_authcodeflow/management/commands/__init__.py
oauth2_authcodeflow/management/commands/oidc_urls.py
oauth2_authcodeflow/management/commands/purge_blacklisted_tokens.py
oauth2_authcodeflow/middleware.py
oauth2_authcodeflow/migrations/0001_initial.py
oauth2_authcodeflow/migrations/0002_auto_20210528_1422.py
oauth2_authcodeflow/migrations/0003_auto_20210528_1432.py
oauth2_authcodeflow/migrations/0004_blacklistedtoken_constraint.py
oauth2_authcodeflow/migrations/0005_alter_blacklistedtoken.py
oauth2_authcodeflow/migrations/0006_alter_id_fields.py
oauth2_authcodeflow/migrations/__init__.py
oauth2_authcodeflow/models.py
oauth2_authcodeflow/py.typed
oauth2_authcodeflow/urls.py
oauth2_authcodeflow/utils.py
oauth2_authcodeflow/views.py
django_oauth2_authcodeflow-1.4.1.dist-info/licenses/LICENSE
django_oauth2_authcodeflow-1.4.1.dist-info/WHEEL
django_oauth2_authcodeflow-1.4.1.dist-info/METADATA
django_oauth2_authcodeflow-1.4.1.dist-info/RECORD
