Metadata-Version: 2.4
Name: django-oauth2-authcodeflow
Version: 1.4.1
Summary: Authenticate with any OpenId Connect/Oauth2 provider through authorization code flow. PKCE is also supported.
Keywords: oauth2,oidc,openid
Author: Cyrille Pontvieux, Befog, Eric Plaster, Gabriel Dugny, Niko Tyni, Pinoatrome, Samir Hachimi, Sebastian Annies
Author-email: Cyrille Pontvieux <cyrille@enialis.net>, Befog <ofogelberg@gmail.com>, Eric Plaster <plaster@gmail.com>, Gabriel Dugny <gabriel.dugny@manomano.com>, Niko Tyni <ntyni@cc.helsinki.fi>, Pinoatrome <pinoatrome@users.noreply.github.com>, Samir Hachimi <shachimi@systra.com>, Sebastian Annies <Sebastian.Annies@gmail.com>
License-Expression: MIT
License-File: LICENSE
Classifier: Development Status :: 5 - Production/Stable
Classifier: Intended Audience :: Developers
Classifier: Natural Language :: English
Classifier: Operating System :: OS Independent
Classifier: Environment :: Web Environment
Classifier: Programming Language :: Python :: 3.10
Classifier: Programming Language :: Python :: 3.11
Classifier: Programming Language :: Python :: 3.12
Classifier: Programming Language :: Python :: 3.13
Classifier: Programming Language :: Python :: 3.14
Classifier: Framework :: Django
Classifier: Framework :: Django :: 4.2
Classifier: Framework :: Django :: 5.0
Classifier: Framework :: Django :: 5.1
Classifier: Framework :: Django :: 5.2
Classifier: Framework :: Django :: 6.0
Classifier: Topic :: Internet :: WWW/HTTP :: Session
Classifier: Topic :: Security
Classifier: Topic :: Software Development :: Libraries :: Python Modules
Classifier: Typing :: Typed
Requires-Dist: django>=4.2
Requires-Dist: python-jose[cryptography]>=3.3
Requires-Dist: requests>=2.28
Maintainer: Cyrille Pontvieux
Maintainer-email: Cyrille Pontvieux <cyrille@enialis.net>
Requires-Python: >=3.10
Project-URL: Bug Tracker, https://gitlab.com/snake_coders/django-oauth2-authcodeflow/-/issues
Project-URL: Changelog, https://gitlab.com/snake_coders/django-oauth2-authcodeflow/-/blob/master/CHANGELOG.md
Project-URL: Contributing, https://gitlab.com/snake_coders/django-oauth2-authcodeflow/-/blob/master/CONTRIBUTING.md
Project-URL: Documentation, https://gitlab.com/snake_coders/django-oauth2-authcodeflow/-/blob/master/README.md
Project-URL: Github mirror, https://github.com/jrd/django-oauth2-authcodeflow
Project-URL: Merge Requests, https://gitlab.com/snake_coders/django-oauth2-authcodeflow/-/merge_requests
Project-URL: Repository, https://gitlab.com/snake_coders/django-oauth2-authcodeflow
